bakapiv2.py
bakapi_v2-0.4.dist-info/LICENSE
bakapi_v2-0.4.dist-info/METADATA
bakapi_v2-0.4.dist-info/WHEEL
bakapi_v2-0.4.dist-info/top_level.txt
bakapi_v2-0.4.dist-info/RECORD
