Metadata-Version: 2.1
Name: bakapi-v2
Version: 0.4
Summary: Klient k API Bakalářů v jazyce Python.
Home-page: https://github.com/MortikCZ/bakapi-v2
Author: Lukáš S., mwolfik
Project-URL: Documentation, https://github.com/MortikCZ/bakapi-v2/blob/main/README.md
Project-URL: Source Code, https://github.com/MortikCZ/bakapi-v2/blob/main/bakapi-v2.py
Project-URL: License, https://github.com/MortikCZ/bakapi-v2/blob/main/LICENSE
Project-URL: Issues, https://github.com/MortikCZ/bakapi-v2/issues
Classifier: Development Status :: 4 - Beta
Classifier: Programming Language :: Python :: 3
Classifier: License :: OSI Approved :: MIT License
Classifier: Operating System :: OS Independent
Classifier: Natural Language :: Czech
Requires-Python: >=3.6
License-File: LICENSE
Requires-Dist: requests
